spacy_polarity/__init__.py
spacy_polarity/_transformers.py
spacy_polarity/_version.py
spacy_polarity/types.py
spacy_polarity-0.1.3.dist-info/LICENSE
spacy_polarity-0.1.3.dist-info/METADATA
spacy_polarity-0.1.3.dist-info/WHEEL
spacy_polarity-0.1.3.dist-info/top_level.txt
spacy_polarity-0.1.3.dist-info/RECORD
