Metadata-Version: 2.2
Name: spacy-polarity
Version: 0.1.3
Summary: Spacy extension for sentiment polarity
Author: sondalex
License: MIT License
Project-URL: homepage, https://github.com/sondalex/spacy-polarity
Project-URL: documentation, https://github.com/sondalex/spacy-polarity
Requires-Python: >=3.10
License-File: LICENSE
Requires-Dist: spacy>=3.1.0
Requires-Dist: textblob>=0.19.0
Requires-Dist: numpy<2.0.0
Provides-Extra: test
Requires-Dist: pytest; extra == "test"
Provides-Extra: docs
Requires-Dist: sphinx; extra == "docs"
Provides-Extra: transformers
Requires-Dist: transformers; extra == "transformers"
Requires-Dist: torch; extra == "transformers"
